proapi/__init__.py
proapi/__main__.py
proapi/auth/http_auth.py
proapi/auth/jwt.py
proapi/auth/login.py
proapi/auth/principal.py
proapi/auth/user.py
proapi/core/__init__.py
proapi/core/__main__.py
proapi/core/cli.py
proapi/core/core.py
proapi/core/docs.py
proapi/core/logging.py
proapi/core/run.py
proapi/core/swagger_ui.py
proapi/cython_ext/__init__.py
proapi/performance/optimized.py
proapi/performance/scheduler.py
proapi/routing/middleware.py
proapi/routing/request_proxy.py
proapi/routing/routing.py
proapi/server/asgi.py
proapi/server/asgi_adapter.py
proapi/server/asgi_adapter_fix.py
proapi/server/asgi_app.py
proapi/server/server.py
proapi/session/session.py
proapi/session/session_proxy.py
proapi/templates/templating.py
proapi/utils/forwarding.py
proapi/utils/helpers.py
proapi/utils/utils.py
proapi/utils/worker_manager.py
proapi/websocket/websocket.py
proapi/websocket/websocket_middleware.py
proapi-0.4.4.dist-info/licenses/LICENSE
proapi-0.4.4.dist-info/METADATA
proapi-0.4.4.dist-info/WHEEL
proapi-0.4.4.dist-info/entry_points.txt
proapi-0.4.4.dist-info/top_level.txt
proapi-0.4.4.dist-info/RECORD
