Metadata-Version: 2.4
Name: proapi
Version: 0.4.4
Summary: A lightweight, beginner-friendly yet powerful Python web framework - simpler than Flask, faster than FastAPI
Author-email: ProAPI Team <proapi@example.com>
License-Expression: MIT
Project-URL: Homepage, https://github.com/GrandpaEJ/ProAPI
Project-URL: Documentation, https://github.com/GrandpaEJ/ProAPI/docs
Project-URL: Repository, https://github.com/GrandpaEJ/ProAPI
Project-URL: Issues, https://github.com/GrandpaEJ/ProAPI/issues
Classifier: Development Status :: 4 - Beta
Classifier: Intended Audience :: Developers
Classifier: Programming Language :: Python :: 3
Classifier: Programming Language :: Python :: 3.8
Classifier: Programming Language :: Python :: 3.9
Classifier: Programming Language :: Python :: 3.10
Classifier: Programming Language :: Python :: 3.11
Classifier: Programming Language :: Python :: 3.12
Classifier: Programming Language :: Python :: 3.13
Classifier: Topic :: Internet :: WWW/HTTP :: Dynamic Content
Classifier: Topic :: Internet :: WWW/HTTP :: WSGI :: Application
Classifier: Topic :: Internet :: WWW/HTTP :: HTTP Servers
Classifier: Topic :: Software Development :: Libraries :: Application Frameworks
Requires-Python: >=3.8
License-File: LICENSE
Requires-Dist: loguru>=0.7.2
Requires-Dist: uvicorn>=0.27.0
Requires-Dist: jinja2>=3.1.3
Requires-Dist: watchdog>=3.0.0
Requires-Dist: pydantic>=2.6.0
Requires-Dist: psutil>=5.9.8
Requires-Dist: httpx>=0.26.0
Requires-Dist: python-multipart>=0.0.7
Provides-Extra: dev
Requires-Dist: pytest>=7.4.3; extra == "dev"
Requires-Dist: pytest-cov>=4.1.0; extra == "dev"
Requires-Dist: black>=23.12.0; extra == "dev"
Requires-Dist: isort>=5.13.0; extra == "dev"
Requires-Dist: flake8>=6.1.0; extra == "dev"
Requires-Dist: mypy>=1.7.0; extra == "dev"
Provides-Extra: prod
Requires-Dist: gunicorn>=21.2.0; extra == "prod"
Requires-Dist: python-dotenv>=1.0.0; extra == "prod"
Requires-Dist: hypercorn>=0.15.0; extra == "prod"
Provides-Extra: cloudflare
Requires-Dist: cloudflared>=0.1.0; extra == "cloudflare"
Provides-Extra: cython
Requires-Dist: cython>=3.0.6; extra == "cython"
Provides-Extra: docs
Requires-Dist: sphinx>=7.2.6; extra == "docs"
Requires-Dist: sphinx-rtd-theme>=1.3.0; extra == "docs"
Requires-Dist: sphinx-autodoc-typehints>=1.25.2; extra == "docs"
Provides-Extra: full
Requires-Dist: gunicorn>=21.2.0; extra == "full"
Requires-Dist: python-dotenv>=1.0.0; extra == "full"
Requires-Dist: cloudflared>=0.1.0; extra == "full"
Requires-Dist: cython>=3.0.6; extra == "full"
Requires-Dist: hypercorn>=0.15.0; extra == "full"
Requires-Dist: sphinx>=7.2.6; extra == "full"
Requires-Dist: sphinx-rtd-theme>=1.3.0; extra == "full"
Dynamic: license-file
